GooeyEx/__init__.py
GooeyEx/__main__.py
GooeyEx/gui/__init__.py
GooeyEx/gui/bootstrap.py
GooeyEx/gui/cli.py
GooeyEx/gui/constants.py
GooeyEx/gui/events.py
GooeyEx/gui/formatters.py
GooeyEx/gui/host.py
GooeyEx/gui/image_repository.py
GooeyEx/gui/imageutil.py
GooeyEx/gui/processor.py
GooeyEx/gui/pubsub.py
GooeyEx/gui/seeder.py
GooeyEx/gui/state.py
GooeyEx/gui/three_to_four.py
GooeyEx/gui/validation.py
GooeyEx/gui/validators.py
GooeyEx/gui/application/__init__.py
GooeyEx/gui/application/application.py
GooeyEx/gui/application/components.py
GooeyEx/gui/components/__init__.py
GooeyEx/gui/components/config.py
GooeyEx/gui/components/console.py
GooeyEx/gui/components/dialogs.py
GooeyEx/gui/components/footer.py
GooeyEx/gui/components/header.py
GooeyEx/gui/components/menubar.py
GooeyEx/gui/components/modals.py
GooeyEx/gui/components/mouse.py
GooeyEx/gui/components/sidebar.py
GooeyEx/gui/components/tabbar.py
GooeyEx/gui/components/filtering/__init__.py
GooeyEx/gui/components/filtering/prefix_filter.py
GooeyEx/gui/components/layouts/__init__.py
GooeyEx/gui/components/layouts/layouts.py
GooeyEx/gui/components/options/__init__.py
GooeyEx/gui/components/options/options.py
GooeyEx/gui/components/options/validators.py
GooeyEx/gui/components/util/__init__.py
GooeyEx/gui/components/util/wrapped_static_text.py
GooeyEx/gui/components/widgets/__init__.py
GooeyEx/gui/components/widgets/bases.py
GooeyEx/gui/components/widgets/basictextconsole.py
GooeyEx/gui/components/widgets/checkbox.py
GooeyEx/gui/components/widgets/choosers.py
GooeyEx/gui/components/widgets/command.py
GooeyEx/gui/components/widgets/counter.py
GooeyEx/gui/components/widgets/dropdown.py
GooeyEx/gui/components/widgets/dropdown_filterable.py
GooeyEx/gui/components/widgets/listbox.py
GooeyEx/gui/components/widgets/numeric_fields.py
GooeyEx/gui/components/widgets/password.py
GooeyEx/gui/components/widgets/radio_group.py
GooeyEx/gui/components/widgets/richtextconsole.py
GooeyEx/gui/components/widgets/slider.py
gooeyex-0.1.0.dist-info/licenses/LICENSE.txt
gooeyex-0.1.0.dist-info/METADATA
gooeyex-0.1.0.dist-info/WHEEL
gooeyex-0.1.0.dist-info/dependency_links.txt
gooeyex-0.1.0.dist-info/top_level.txt
gooeyex-0.1.0.dist-info/RECORD
