Metadata-Version: 2.4
Name: GooeyEx
Version: 0.1.0
Summary: GooeyEx is a fork of Gooey with (Ex)tended features and bugfixes.
Home-page: http://pypi.python.org/pypi/GooeyEx/
Author: greats3an
Author-email: greats3an@gmail.com
License: MIT
Classifier: Development Status :: 4 - Beta
Classifier: Intended Audience :: Developers
Classifier: Topic :: Desktop Environment
Classifier: Topic :: Software Development :: Build Tools
Classifier: Topic :: Software Development :: Widget Sets
Classifier: Programming Language :: Python :: 3
Classifier: License :: OSI Approved :: MIT License
Requires-Python: >=3.6
License-File: LICENSE.txt
Requires-Dist: Pillow>=4.3.0
Requires-Dist: psutil>=5.4.2
Requires-Dist: colored>=1.3.93
Requires-Dist: pygtrie>=2.3.3
Requires-Dist: typing-extensions>=3.10.0.2
Requires-Dist: wxpython>=4.2.0
Requires-Dist: dataclasses>=0.8; python_version < "3.7"
Dynamic: author
Dynamic: author-email
Dynamic: classifier
Dynamic: description
Dynamic: description-content-type
Dynamic: home-page
Dynamic: license
Dynamic: license-file
Dynamic: requires-dist
Dynamic: requires-python
Dynamic: summary
